Workbook

Sheet README
A1: KRA Elasticity Forecast Engine - Input Workbook
A2: Purpose | B2: Input template for the Python-based medium-term revenue forecast engine. It preserves the baseline Excel/schema logic and adds a controlled Iran / Middle East conflict scenario layer for revenue shock analysis.
A3: How to use | B3: 1) Update yellow cells only. 2) Keep internal tax-head names unchanged. 3) Select year, scenario, and mode in Control. 4) Enter or revise Iran / Middle East conflict shocks in CGE_Scenarios as decimal shocks (e.g., -0.020 for -2.0 pp). 5) Run the Python workflow against this workbook to produce forecast, scenario, monthly, dashboard, and export outputs.
A4: Key design rule | B4: Baseline mode preserves the current Excel/schema logic. Improved mode keeps the same baseline architecture but allows the enhanced driver columns already stored in Tax_Heads_Input to be used where applicable.
A5: Scenario rule | B5: Iran scenarios shock macro drivers only. Revenue logic, opening bases, bridge identities, policy additions, and targets remain governed by the same workbook schema.
A6: Target handling note | B6: Targets are exogenous. Policy measures are exogenous additive or subtractive adjustments at the applicable tax line. Blank targets are intentional and should remain blank rather than being coerced to zero.
A7: Bridge identities | B7: Import Excise Duty must reconcile to Excise Duty Oil + Excise Duty Ordinary + Less Provision for Refunds. VAT, imports must reconcile to VAT Imports Ordinary + VAT Imports Oil.
A8: Control governance | B8: Control is the official entry sheet for selected year, selected scenario, mode, current fiscal year, reference share year, scenario allocation mode, scenario duration months, and lock-actual-months choice.
A9: Scenario governance | B9: CGE_Scenarios is the official scenario source. Do not hardcode scenario shocks in Python or Streamlit once workbook-driven scenario loading is activated.
A10: Iran scenario set | B10: The workbook includes Baseline, Severe_1m, Severe_3m, Severe_gt3m, Corrective_3m, Corrective_gt3m, Oil_spike_only, Shipping_disruption_only, and Composite_Iran_War rows.
A11: Shock channels | B11: Core shock channels are GDP, deflator, CPI, wages, imports, exports, non-oil imports, oil volume, oil world price, profitability, and exchange-rate-sensitive proxy shock.
A12: Files | B12: This workbook is paired with Python scripts that read these sheets and produce forecast outputs, risk diagnostics, annex summaries, and scenario packs.
A13: Source reference | B13: Logic is based on the uploaded KRA model logic, elasticity mapping, modelling scheme workbook, and the governance instructions shared in this conversation.
... A15: Purple fill | B15: Control selections / governance settings

Sheet Control
A1: Control Item | B1: Value
A2: Selected Year | B2: 2025/26
A3: Selected Scenario | B3: Baseline
A4: Mode | B4: baseline
A5: Current Fiscal Year | B5: 2025/26
A6: Reference Share Year | B6: 2024/25
A7: Scenario Allocation Mode | B7: remaining_only
A8: Scenario Duration Months | B8: 3
A9: Lock Actual Months | B9: Y
A10: Notes | B10: Baseline preserves schema; Iran scenarios shock macro drivers only. Edit yellow cells only.

Sheet Macro_Baseline
A1: Variable | B1: 2025/26 | C1: 2026/27 | D1: 2027/28 | E1: Type | F1: Notes
A2: Real GDP growth | B2: 0.055 | C2: 0.053 | D2: 0.053 | E2: input | F2: 2025/26 from shared logic; later years prefilled for review
A3: GDP deflator | B3: 0.057 | C3: 0.054 | D3: 0.054 | E3: input | F3: 2025/26 from shared logic
A4: Nominal GDP growth | B4: =(1+B2)*(1+B3)-1 -> 0.115135 | C4: =(1+C2)*(1+C3)-1 -> 0.109862 | D4: =(1+D2)*(1+D3)-1 -> 0.109862 | E4: formula | F4: Derived
A5: CPI | B5: 0.05 | C5: 0.048 | D5: 0.048 | E5: input | F5: 2025/26 from shared logic
A6: Wage rate (% change) | B6: =(1.009)*(1+B5)-1 -> 0.05945 | C6: =(1.009)*(1+C5)-1 -> 0.057432 | D6: =(1.009)*(1+D5)-1 -> 0.057432 | E6: formula | F6: Workbook-style helper
A7: Bracket creep | B7: =B5 -> 0.05 | C7: =C5 -> 0.048 | D7: =D5 -> 0.048 | E7: formula | F7: Proxy set equal to CPI unless changed in Python
A8: Import prices (% change) | B8: 0.033 | C8: 0.033 | D8: 0.033 | E8: input | F8: Placeholder if external price file unavailable
A9: Import prices excl. oil products | B9: 0.031 | C9: 0.031 | D9: 0.031 | E9: input | F9: Placeholder if external price file unavailable
A10: Import Value Growth | B10: 0.06 | C10: 0.06 | D10: 0.06 | E10: input | F10: 2025/26 from shared logic; later years review
A11: Export Value Growth | B11: 0.105 | C11: 0.105 | D11: 0.105 | E11: input | F11: 2025/26 from shared logic; later years review
A12: Non oil import value growth (Dry) | B12: 0.06 | C12: 0.06 | D12: 0.06 | E12: input | F12: Can be overridden directly
A13: Oil (% volume change) | B13: 0.033 | C13: 0.033 | D13: 0.033 | E13: input | F13: 2025/26 from shared logic
A14: Oil World price change (in US$) | B14: 0.013 | C14: 0.013 | D14: 0.013 | E14: input | F14: 2025/26 from shared logic
A15: Oil value growth | B15: =(1+B13)*(1+B14)-1 -> 0.046429 | C15: =(1+C13)*(1+C14)-1 -> 0.046429 | D15: =(1+D13)*(1+D14)-1 -> 0.046429 | E15: formula | F15: Derived
A16: Implied profitability growth | B16: =B4 -> 0.115135 | C16: =C4 -> 0.109862 | D16: =D4 -> 0.109862 | E16: formula | F16: Current simplified assumption = nominal GDP growth
A17: Exchange rate change | B17: 0 | C17: 0 | D17: 0 | E17: input | F17: Scenario shock bridge helper

Sheet Elasticities
A1: Parameter | B1: Value | C1: Type | D1: Notes
A2: tariff_non_oil | B2: 0.361 | C2: input | D2: Tariff revenue elasticity with respect to non-oil imports
A3: tariff_oil | B3: 0.397 | C3: input | D3: Tariff revenue elasticity with respect to oil
A4: vat_import_oil_gdp | B4: 0.463 | C4: input | D4: Baseline workbook-style VAT oil driver (baseline mode); improved mode can switch to oil value growth
A5: vat_import_non_oil | B5: 0.308 | C5: input | D5: VAT imports ordinary / non-oil imports
A6: vat_domestic_gdp | B6: 0.38 | C6: input | D6: Domestic VAT to nominal GDP proxy
A7: vat_domestic_cpi | B7: 0.957 | C7: input | D7: Optional enhanced domestic VAT inflation pass-through
A8: paye_gdp | B8: 0.479 | C8: input | D8: Stored for reference
A9: paye_wage | B9: 0.96 | C9: input | D9: PAYE to wage rate
A10: paye_bracket | B10: 0.958 | C10: input | D10: PAYE bracket creep
A11: other_income | B11: 0.452 | C11: input | D11: Other income taxes
A12: excise_oil_gdp | B12: 0.619 | C12: input | D12: Baseline oil excise elasticity
A13: excise_non_oil_imports | B13: 0.241 | C13: input | D13: Excise on non-oil imports
... A21: excise_oil_crude_price | B21: -0.111945 | C21: Oil excise elasticity with respect to oil world price change | D21: Required to match original Excel formula

Sheet Tax_Heads_Input
A1: Department | B1: Revenue Type | C1: Internal Tax Head | D1: Annex Tax Head | E1: Actual 2024/25 | F1: Formula Type | G1: Driver 1 | H1: Elasticity 1 | I1: Driver 2 | J1: Elasticity 2 | K1: Improved Driver 1 | L1: Improved Elasticity 1 | M1: Improved Driver 2 | N1: Improved Elasticity 2 | O1: Notes
A2: Customs | B2: Exchequer | C2: Import Duty Ordinary (net) | D2: Import duty | E2: 150992 | F2: weighted_growth | G2: Non oil import value growth (Dry) | H2: tariff_non_oil | I2: Oil value growth | J2: tariff_oil | K2: Non oil import value growth (Dry) | L2: tariff_non_oil | M2: Oil value growth | N2: tariff_oil | O2: Net import duty line
A3: Customs | B3: Exchequer | C3: Excise Duty Oil | D3: Import Excise Duty | E3: 90826 | F3: excel_oil_excise | G3: Real GDP growth | H3: excise_oil_gdp | K3: Oil value growth | L3: excise_oil_gdp | O3: Enhanced mode lets oil excise respond to oil value growth
A4: Customs | B4: Exchequer | C4: Excise Duty Ordinary | D4: Import Excise Duty | E4: 48707 | F4: excel_oil_excise | G4: Non oil import value growth (Dry) | H4: excise_non_oil_imports | K4: Non oil import value growth (Dry) | L4: excise_non_oil_imports
A5: Customs | B5: Exchequer | C5: Less Provision for Refunds | D5: Import Excise Duty | E5: -480 | F5: constant | O5: Negative row; carried forward unless policy-adjusted
A6: Customs | B6: Exchequer | C6: VAT Imports Ordinary | D6: VAT, imports | E6: 221030 | F6: single_growth | G6: Non oil import value growth (Dry) | H6: vat_import_non_oil | K6: Non oil import value growth (Dry) | L6: vat_import_non_oil
A7: Customs | B7: Exchequer | C7: VAT Imports Oil | D7: VAT, imports | E7: 91611 | F7: single_growth | G7: Real GDP growth | H7: vat_import_oil_gdp | K7: Oil value growth | L7: vat_import_oil_gdp | O7: Enhanced mode lets oil VAT respond to oil value growth
A8: Customs | B8: Exchequer | C8: Anti-adulteration levy | D8: Anti-adulteration levy | E8: 1625 | F8: fixed_growth | G8: aal_default_growth | K8: aal_default_growth | O8: Simple growth assumption
A9: Customs | B9: Exchequer | C9: IDF fees | D9: IDF fees | E9: 51327 | F9: single_growth | G9: Import Value Growth | H9: idf_elasticity | K9: Import Value Growth | L9: idf_elasticity
A10: Customs | B10: Exchequer | C10: Export and Investment Promotion Levy | D10: Export and Investment Promotion Levy | E10: 1786 | F10: single_growth | G10: Export Value Growth | H10: export_levy_elasticity | K10: Export Value Growth | L10: export_levy_elasticity
A11: Customs | B11: Exchequer | C11: Railway Development Levy | D11: Railway Development Levy | E11: 49617 | F11: single_growth | G11: Import Value Growth | H11: rdl_elasticity | K11: Import Value Growth | L11: rdl_elasticity
A12: Domestic | B12: Exchequer | C12: PAYE | D12: PAYE | E12: 624600 | F12: excel_paye_compound | G12: Wage rate (% change) | H12: paye_wage | I12: Bracket creep | J12: paye_bracket | K12: Wage rate (% change) | L12: paye_wage | M12: Bracket creep | N12: paye_bracket
A13: Domestic | B13: Exchequer | C13: Other income taxes | D13: Other income taxes | E13: 498726 | F13: single_growth | G13: Nominal GDP growth | H13: other_income | K13: Nominal GDP growth | L13: other_income | O13: Excludes Turnover Tax in this template
A14: Domestic | B14: Exchequer | C14: Capital Gains Tax | D14: Capital Gains Tax | E14: 6427 | F14: single_growth | G14: Nominal GDP growth | H14: other_income | K14: Nominal GDP growth | L14: other_income
A15: Domestic | B15: Exchequer | C15: Domestic VAT | D15: Domestic VAT | E15: 334436 | F15: excel_growth_cpi | G15: Nominal GDP growth | H15: vat_domestic_gdp | K15: Nominal GDP growth | L15: vat_domestic_gdp | O15: Can later be enhanced with CPI pass-through
A16: Domestic | B16: Exchequer | C16: Excise Domestic | D16: Excise Domestic | E16: 74658 | F16: excel_dual_additive_cpi | G16: Nominal GDP growth | H16: excise_non_oil_domestic | K16: Nominal GDP growth | L16: excise_non_oil_domestic
A17: Domestic | B17: Exchequer | C17: Excise - Financial transactions | D17: Excise - Financial transactions | E17: 47233 | F17: single_growth | G17: Nominal GDP growth | H17: excise_non_oil_domestic | K17: Nominal GDP growth | L17: excise_non_oil_domestic | O17: Maps to money transfer target line
A18: Domestic | B18: Exchequer | C18: Excise on Airtime | D18: Excise on Airtime | E18: 48465 | F18: excel_unit_growth_cpi | G18: Nominal GDP growth | H18: excise_non_oil_domestic | K18: Nominal GDP growth | L18: excise_non_oil_domestic
A19: Domestic | B19: Exchequer | C19: Excise Betting Services | D19: Excise Betting Services | E19: 10504 | F19: single_growth | G19: Nominal GDP growth | H19: excise_non_oil_domestic | K19: Nominal GDP growth | L19: excise_non_oil_domestic
A20: Domestic | B20: Exchequer | C20: Betting Tax | D20: Betting Tax | E20: 4305 | F20: single_growth | G20: Nominal GDP growth | H20: excise_non_oil_domestic | K20: Nominal GDP growth | L20: excise_non_oil_domestic
A21: Domestic | B21: Exchequer | C21: Digital service tax | D21: Digital service tax | E21: 413 | F21: single_growth | G21: Nominal GDP growth | H21: excise_non_oil_domestic | K21: Nominal GDP growth | L21: excise_non_oil_domestic | O21: Acts as DST proxy
A22: Domestic | B22: Exchequer | C22: Rent of Land | D22: Rent of Land | E22: 251 | F22: single_growth | G22: Nominal GDP growth | H22: proxy_nominal | K22: Nominal GDP growth | L22: proxy_nominal
A23: Domestic | B23: Exchequer | C23: Stamp Duty | D23: Stamp Duty | E23: 15292 | F23: single_growth | G23: Nominal GDP growth | H23: proxy_nominal | K23: Nominal GDP growth | L23: proxy_nominal
A24: Domestic | B24: Exchequer | C24: Rental Income | D24: Rental Income | E24: 16463 | F24: single_growth | G24: Nominal GDP growth | H24: proxy_nominal | K24: Nominal GDP growth | L24: proxy_nominal
A25: Domestic | B25: Exchequer | C25: Turnover Tax | D25: Turnover Tax | E25: 1575 | F25: single_growth | G25: Nominal GDP growth | H25: proxy_nominal | K25: Nominal GDP growth | L25: proxy_nominal
A26: Domestic | B26: Exchequer | C26: Surplus Funds | D26: Surplus Funds | E26: 16336 | F26: excel_cpi_then_gap | G26: Nominal GDP growth | H26: proxy_nominal | K26: Nominal GDP growth | L26: proxy_nominal
A27: Traffic | B27: Exchequer | C27: Traffic exchequer Revenue | D27: Traffic exchequer Revenue | E27: 4897 | F27: single_growth | G27: Real GDP growth | H27: traffic_proxy | K27: Nominal GDP growth | L27: traffic_proxy | O27: Improved mode uses nominal GDP instead of real GDP

Sheet Policy_Measures
A1: Internal Tax Head | B1: FA 2025/26 | C1: Admin 2025/26 | D1: EACCMA 2025/26 | E1: FA 2026/27 | F1: Admin 2026/27 | G1: EACCMA 2026/27 | H1: FA 2027/28 | I1: Admin 2027/28 | J1: EACCMA 2027/28 | K1: Notes
A2: Import Duty Ordinary (net) | B2: 0 | C2: 0 | D2: 0 | E2: 0 | F2: 0 | G2: 0 | H2: 0 | I2: 0 | J2: 0 | K2: Enter exogenous impact if applicable
A3: Excise Duty Oil | B3: 0 | C3: 0 | D3: 0 | E3: 0 | F3: 0 | G3: 0 | H3: 0 | I3: 0 | J3: 0
A4: Excise Duty Ordinary | B4: 0 | C4: 0 | D4: 0 | E4: 0 | F4: 0 | G4: 0 | H4: 0 | I4: 0 | J4: 0
A5: Less Provision for Refunds | B5: 0 | C5: 0 | D5: 0 | E5: 0 | F5: 0 | G5: 0 | H5: 0 | I5: 0 | J5: 0
A6: VAT Imports Ordinary | B6: 0 | C6: 0 | D6: 0 | E6: 0 | F6: 0 | G6: 0 | H6: 0 | I6: 0 | J6: 0
A7: VAT Imports Oil | B7: 0 | C7: 0 | D7: 0 | E7: 0 | F7: 0 | G7: 0 | H7: 0 | I7: 0 | J7: 0
A8: Anti-adulteration levy | B8: 0 | C8: 0 | D8: 0 | E8: 0 | F8: 0 | G8: 0 | H8: 0 | I8: 0 | J8: 0
A9: IDF fees | B9: 0 | C9: 0 | D9: 0 | E9: 0 | F9: 0 | G9: 0 | H9: 0 | I9: 0 | J9: 0
A10: Export and Investment Promotion Levy | B10: 0 | C10: 0 | D10: 0 | E10: 0 | F10: 0 | G10: 0 | H10: 0 | I10: 0 | J10: 0
A11: Railway Development Levy | B11: 0 | C11: 0 | D11: 0 | E11: 0 | F11: 0 | G11: 0 | H11: 0 | I11: 0 | J11: 0
A12: PAYE | B12: 0 | C12: 0 | D12: 0 | E12: 0 | F12: 0 | G12: 0 | H12: 0 | I12: 0 | J12: 0
A13: Other income taxes | B13: 0 | C13: 0 | D13: 0 | E13: 0 | F13: 0 | G13: 0 | H13: 0 | I13: 0 | J13: 0
A14: Capital Gains Tax | B14: 0 | C14: 0 | D14: 0 | E14: 0 | F14: 0 | G14: 0 | H14: 0 | I14: 0 | J14: 0
... A27: Traffic exchequer Revenue | B27: 0 | C27: 0 | D27: 0 | E27: 0 | F27: 0 | G27: 0 | H27: 0 | I27: 0 | J27: 0

Sheet Targets
A1: Annex Tax Head | B1: Target 2025/26 | C1: Target 2026/27 | D1: Target 2027/28 | E1: Notes
A2: Import duty | B2: 162851 | C2: 179918 | D2: 208828 | E2: Mapped to net import duty target
A3: Import Excise Duty | B3: 141678 | C3: 157374 | D3: 176494 | E3: Mapped to net excise duty target
A4: VAT, imports | B4: 388502 | C4: 378502 | D4: 552271 | E4: Mapped to net VAT - imports target
A5: Anti-adulteration levy | B5: 1449 | C5: 1046 | D5: 1153
A6: IDF fees | B6: 60544 | C6: 68347 | D6: 74509 | E6: Import Declaration Fees
A7: Export and Investment Promotion Levy | E7: Blank in supplied target sheet
A8: Railway Development Levy | B8: 40694 | C8: 45000 | D8: 49700
A9: PAYE | B9: 652374 | C9: 749253 | D9: 829975
A10: Other income taxes | B10: 627445 | C10: 737161 | D10: 814326 | E10: Aggregate Other Income Tax net of Turnover Tax
A11: Capital Gains Tax | B11: 5145 | C11: 5685 | D11: 6282
A12: Domestic VAT | B12: 383202 | C12: 435658 | D12: 472044
A13: Excise Domestic | B13: 77241 | C13: 85797 | D13: 96222
A14: Excise - Financial transactions | B14: 57695 | C14: 64086 | D14: 71873 | E14: Mapped from Excise Tax on Money Transfer
A15: Excise on Airtime | B15: 44110 | C15: 48997 | D15: 54950
A16: Excise Betting Services | B16: 14808 | C16: 16448 | D16: 18446
A17: Betting Tax | B17: 11441 | C17: 11441 | D17: 10942
A18: Digital service tax | B18: 491 | C18: 579 | D18: 642 | E18: DST
A19: Rent of Land | E19: Blank in supplied target sheet
A20: Stamp Duty | E20: Blank in supplied target sheet
A21: Rental Income | B21: 18660 | C21: 22001 | D21: 24371
A22: Turnover Tax | B22: 507 | C22: 597 | D22: 662
A23: Surplus Funds | E23: Blank in supplied target sheet
A24: Traffic exchequer Revenue | B24: 3797 | C24: 5372 | D24: 6390
A25: Total Exchequer | B25: 2692634 | C25: 3013263 | D25: 3470081 | E25: Exogenous total exchequer target

Sheet CGE_Scenarios
A1: Scenario | B1: Description | C1: Real GDP growth shock | D1: GDP deflator shock | E1: CPI shock | F1: Wage growth shock | G1: Import Value Growth shock | H1: Export Value Growth shock | I1: Non oil import value growth shock | J1: Oil volume shock | K1: Oil world price shock | L1: Profitability growth shock | M1: Exchange rate shock | N1: Notes
A2: Baseline | B2: No shock / official baseline | C2: 0 | D2: 0 | E2: 0 | F2: 0 | G2: 0 | H2: 0 | I2: 0 | J2: 0 | K2: 0 | L2: 0 | M2: 0 | N2: Reference row for baseline
A3: Severe_1m | B3: Severe Iran / Middle East conflict shock lasting about 1 month | C3: 0 | D3: 0 | E3: 0 | F3: 0 | G3: 0 | H3: 0 | I3: 0 | J3: 0 | K3: 0 | L3: 0 | M3: 0 | N3: Short duration severe shock; editable
A4: Severe_3m | B4: Severe Iran / Middle East conflict shock lasting about 3 months | C4: 0 | D4: 0 | E4: 0 | F4: 0 | G4: 0 | H4: 0 | I4: 0 | J4: 0 | K4: 0 | L4: 0 | M4: 0 | N4: Main short-to-medium conflict shock; editable
A5: Severe_gt3m | B5: Severe Iran / Middle East conflict shock lasting more than 3 months | C5: 0 | D5: 0 | E5: 0 | F5: 0 | G5: 0 | H5: 0 | I5: 0 | J5: 0 | K5: 0 | L5: 0 | M5: 0 | N5: Extended conflict shock; editable
A6: Corrective_3m | B6: Conflict shock with corrective policy / adjustment response over about 3 months | C6: 0 | D6: 0 | E6: 0 | F6: 0 | G6: 0 | H6: 0 | I6: 0 | J6: 0 | K6: 0 | L6: 0 | M6: 0 | N6: Use when mitigation offsets part of the severe case
A7: Corrective_gt3m | B7: Extended conflict shock with corrective policy / adjustment response | C7: 0 | D7: 0 | E7: 0 | F7: 0 | G7: 0 | H7: 0 | I7: 0 | J7: 0 | K7: 0 | L7: 0 | M7: 0 | N7: Use when mitigation is phased over a longer duration
A8: Oil_spike_only | B8: Oil-only shock without broad shipping disruption | C8: 0 | D8: 0 | E8: 0 | F8: 0 | G8: 0 | H8: 0 | I8: 0 | J8: 0 | K8: 0 | L8: 0 | M8: 0 | N8: Use for pure oil-price pass-through testing
A9: Shipping_disruption_only | B9: Trade / shipping disruption without standalone oil spike emphasis | C9: 0 | D9: 0 | E9: 0 | F9: 0 | G9: 0 | H9: 0 | I9: 0 | J9: 0 | K9: 0 | L9: 0 | M9: 0 | N9: Use for logistics and imports-only testing
A10: Composite_Iran_War | B10: Combined oil, shipping, and macro spillover shock | C10: 0 | D10: 0 | E10: 0 | F10: 0 | G10: 0 | H10: 0 | I10: 0 | J10: 0 | K10: 0 | L10: 0 | M10: 0 | N10: Main composite Iran-war scenario

Sheet Annex_Template
A1: Tax head | B1: Projected Collection 2025/26 | C1: Target 2025/26 | D1: Revenue Risk
A2: Import duty
A3: Import Excise Duty
A4: VAT, imports
A5: Anti-adulteration levy
A6: IDF fees
A7: Export and Investment Promotion Levy
A8: Railway Development Levy
A9: PAYE
A10: Other income taxes
A11: Capital Gains Tax
A12: Domestic VAT
A13: Excise Domestic
... A25: Total Exchequer

Sheet Validation_Checks
A1: Check | B1: Result | C1: Comment
A2: Tax heads in Tax_Heads_Input | B2: =COUNTA(Tax_Heads_Input!$C$2:$C$200) -> 26 | C2: Should match rows in Policy_Measures excluding header
A3: Tax heads in Policy_Measures | B3: =COUNTA(Policy_Measures!$A$2:$A$200) -> 26 | C3: Should match Tax_Heads_Input
A4: Selected year valid | B4: =IF(OR(Control!$B$2="2025/26",Control!$B$2="2026/27",Control!$B$2="2027/28"),"Yes","No") -> Yes | C4: Control!B2 must be a supported forecast year
A5: Selected scenario exists | B5: =IF(COUNTIF(CGE_Scenarios!$A$2:$A$100,Control!$B$3)>0,"Yes","No") -> Yes | C5: Control!B3 must match a scenario row
A6: Control mode valid | B6: =IF(OR(Control!$B$4="baseline",Control!$B$4="improved"),"Yes","No") -> Yes | C6: Mode must be baseline or improved
A7: Iran scenario rows present | B7: =IF(AND(COUNTIF(CGE_Scenarios!$A:$A,"Severe_1m")>0,COUNTIF(CGE_Scenarios!$A:$A,"Severe_3m")>0,COUNTIF(CGE_Scenarios!$A:$A,"Severe_gt3m")>0,COUNTIF(CGE_Scenarios!$A:$A,"Corrective_3m")>0,COUNTIF(CGE_Scenarios!$A:$A,"Corrective_gt3m")>0,COUNTIF(CGE_Scenarios!$A:$A,"Oil_spike_only")>0,COUNTIF(CGE_Scenarios!$A:$A,"Shipping_disruption_only")>0,COUNTIF(CGE_Scenarios!$A:$A,"Composite_Iran_War")>0),"Yes","No") -> Yes | C7: Required Iran conflict scenario set should exist
A8: Shock header set complete | B8: =IF(COUNTA(CGE_Scenarios!$C$1:$M$1)=11,"Yes","No") -> Yes | C8: Core shock columns required for revenue simulation
A9: Blank target cells kept blank | B9: =IF(COUNTBLANK(Targets!$B$2:$D$200)>0,"Yes","No") -> Yes | C9: Blank targets are intentional and should not be coerced to zero
A10: Refund provision retained at 480 | B10: =IF(ABS(INDEX(Tax_Heads_Input!$E$2:$E$200,MATCH("Less Provision for Refunds",Tax_Heads_Input!$C$2:$C$200,0))+480)<0.0001,"Yes","No") -> Yes | C10: Less Provision for Refunds should remain -480 unless intentionally changed
A11: Baseline row no shock | B11: =IF(COUNTIF(CGE_Scenarios!$C$2:$M$2,0)=11,"Yes","No") -> Yes | C11: Baseline row should remain all-zero unless intentionally redefined
